{
    "Header": {
        "data_specs_version": "GCModelDev v0.0.22", 
        "cmor_version": "3.5", 
        "table_id": "Table GCAmonUV", 
        "realm": "atmos atmosChem", 
        "table_date": "28 May 2020", 
        "missing_value": "1e20", 
        "int_missing_value": "-999", 
        "product": "model-output", 
        "approx_interval": "30.00000", 
        "generic_levels": "alevel alevhalf", 
        "mip_era": "GCModelDev", 
        "Conventions": "CF-1.7 CMIP-6.2"
    }, 
    "variable_entry": {
        "hus": {
            "frequency": "mon", 
            "modeling_realm": "atmos", 
            "standard_name": "specific_humidity", 
            "units": "1", 
            "cell_methods": "time: mean", 
            "cell_measures": "area: areacella", 
            "long_name": "Specific Humidity", 
            "comment": "Specific humidity is the mass fraction of water vapor in (moist) air.", 
            "dimensions": "longitude latitude plev19 time", 
            "out_name": "hus", 
            "type": "real", 
            "positive": "", 
            "valid_min": "", 
            "valid_max": "", 
            "ok_min_mean_abs": "", 
            "ok_max_mean_abs": ""
        }, 
        "wap": {
            "frequency": "mon", 
            "modeling_realm": "atmos", 
            "standard_name": "lagrangian_tendency_of_air_pressure", 
            "units": "Pa s-1", 
            "cell_methods": "time: mean", 
            "cell_measures": "area: areacella", 
            "long_name": "Omega (=dp/dt)", 
            "comment": "Omega (vertical velocity in pressure coordinates, positive downwards)", 
            "dimensions": "longitude latitude plev19 time", 
            "out_name": "wap", 
            "type": "real", 
            "positive": "", 
            "valid_min": "", 
            "valid_max": "", 
            "ok_min_mean_abs": "", 
            "ok_max_mean_abs": ""
        }
    }
}
